<?xml version="1.0" encoding="UTF-8" standalone="no"?>
<!-- Generated 23 Jul, 2024 8:38:27 AM by Hibernate Tools 5.0.6.Final --><!DOCTYPE hibernate-mapping PUBLIC "-//Hibernate/Hibernate Mapping DTD 3.0//EN" "http://www.hibernate.org/dtd/hibernate-mapping-3.0.dtd">
<hibernate-mapping auto-import="true" default-access="property"
	default-cascade="none" default-lazy="true">
	<class catalog="sys" dynamic-insert="false" dynamic-update="false"
		mutable="true" name="com.echoes.DTO.HostSummaryByFileIo"
		optimistic-lock="version" polymorphism="implicit"
		select-before-update="false" table="host_summary_by_file_io">
		<comment>VIEW</comment>
		<composite-id class="com.echoes.DTO.HostSummaryByFileIoId"
			mapped="false" name="id" unsaved-value="undefined">
			<key-property name="host" type="string">
				<column name="host" />
			</key-property>
			<key-property name="ios" type="big_decimal">
				<column name="ios" precision="42" scale="0" />
			</key-property>
			<key-property name="ioLatency" type="string">
				<column length="11" name="io_latency" />
			</key-property>
		</composite-id>
	</class>
</hibernate-mapping>
